kbve_atlas/OAI_CONFIG_LIST.json
kbve_atlas/__init__.py
kbve_atlas/api/__init__.py
kbve_atlas/api/api_connector.py
kbve_atlas/api/clients/__init__.py
kbve_atlas/api/clients/chrome_client.py
kbve_atlas/api/clients/coindesk_client.py
kbve_atlas/api/clients/groq_client.py
kbve_atlas/api/clients/novnc_client.py
kbve_atlas/api/clients/poetry_db_client.py
kbve_atlas/api/clients/runelite_client.py
kbve_atlas/api/clients/screen_client.py
kbve_atlas/api/clients/websocket_echo_client.py
kbve_atlas/api/utils/__init__.py
kbve_atlas/api/utils/broadcast_utils.py
kbve_atlas/api/utils/cors_utils.py
kbve_atlas/api/utils/dynamic_endpoint_utils.py
kbve_atlas/api/utils/image_utils.py
kbve_atlas/api/utils/kr_decorator.py
kbve_atlas/api/utils/rss_utils.py
kbve_atlas/api/utils/theme_core.py
kbve_atlas/atlas_autogen.py
kbve_atlas/bigman.py
kbve_atlas/games/__init__.py
kbve_atlas/games/doom.py
kbve_atlas/games/enter_the_matrix.py
kbve_atlas/games/memetris.py
kbve_atlas/games/pacman.py
kbve_atlas/games/snake.py
kbve_atlas/games/tetris.py
kbve_atlas/hello.py
kbve_atlas/models/__init__.py
kbve_atlas/models/coindesk.py
kbve_atlas/models/groq.py
kbve_atlas/models/poem.py
kbve_atlas/models/rsps.py
kbve_atlas/models/rss.py
kbve-1.0.13.dist-info/METADATA
kbve-1.0.13.dist-info/WHEEL
kbve-1.0.13.dist-info/RECORD
