Metadata-Version: 2.1
Name: kbve
Version: 1.0.13
Summary: ATLAS
License: Proprietary
Requires-Python: >=3.10,<3.13
Classifier: License :: Other/Proprietary License
Classifier: Programming Language :: Python :: 3
Classifier: Programming Language :: Python :: 3.10
Classifier: Programming Language :: Python :: 3.11
Classifier: Programming Language :: Python :: 3.12
Requires-Dist: aiohttp (==3.9.5) ; python_version >= "3.10" and python_version < "3.13"
Requires-Dist: aiosignal (==1.3.1) ; python_version >= "3.10" and python_version < "3.13"
Requires-Dist: annotated-types (==0.6.0) ; python_version >= "3.10" and python_version < "3.13"
Requires-Dist: anyio (==4.3.0) ; python_version >= "3.10" and python_version < "3.13"
Requires-Dist: async-timeout (==4.0.3) ; python_version >= "3.10" and python_full_version < "3.11.3"
Requires-Dist: asyncio-redis (==0.16.0) ; python_version >= "3.10" and python_version < "3.13"
Requires-Dist: attrs (==23.2.0) ; python_version >= "3.10" and python_version < "3.13"
Requires-Dist: beautifulsoup4 (==4.12.3) ; python_version >= "3.10" and python_version < "3.13"
Requires-Dist: behave (==1.2.6) ; python_version >= "3.10" and python_version < "3.13"
Requires-Dist: broadcaster[redis] (==0.2.0) ; python_version >= "3.10" and python_version < "3.13"
Requires-Dist: certifi (==2024.2.2) ; python_version >= "3.10" and python_version < "3.13"
Requires-Dist: cffi (==1.16.0) ; python_version >= "3.10" and python_version < "3.13" and (os_name == "nt" or platform_python_implementation != "PyPy") and (implementation_name != "pypy" or platform_python_implementation != "PyPy")
Requires-Dist: chardet (==5.2.0) ; python_version >= "3.10" and python_version < "3.13"
Requires-Dist: charset-normalizer (==3.3.2) ; python_version >= "3.10" and python_version < "3.13"
Requires-Dist: click (==8.1.7) ; python_version >= "3.10" and python_version < "3.13"
Requires-Dist: colorama (==0.4.6) ; python_version >= "3.10" and python_version < "3.13"
Requires-Dist: cryptography (==42.0.7) ; python_version >= "3.10" and python_version < "3.13"
Requires-Dist: cssselect (==1.2.0) ; python_version >= "3.10" and python_version < "3.13"
Requires-Dist: diskcache (==5.6.3) ; python_version >= "3.10" and python_version < "3.13"
Requires-Dist: distro (==1.9.0) ; python_version >= "3.10" and python_version < "3.13"
Requires-Dist: docker (==7.0.0) ; python_version >= "3.10" and python_version < "3.13"
Requires-Dist: exceptiongroup (==1.2.1) ; python_version >= "3.10" and python_version < "3.13"
Requires-Dist: execnet (==2.1.1) ; python_version >= "3.10" and python_version < "3.13"
Requires-Dist: fastapi (==0.110.3) ; python_version >= "3.10" and python_version < "3.13"
Requires-Dist: fasteners (==0.19) ; python_version >= "3.10" and python_version < "3.13"
Requires-Dist: filelock (==3.14.0) ; python_version >= "3.10" and python_version < "3.13"
Requires-Dist: flaml (==2.1.2) ; python_version >= "3.10" and python_version < "3.13"
Requires-Dist: frozenlist (==1.4.1) ; python_version >= "3.10" and python_version < "3.13"
Requires-Dist: fsspec (==2024.5.0) ; python_version >= "3.10" and python_version < "3.13"
Requires-Dist: h11 (==0.14.0) ; python_version >= "3.10" and python_version < "3.13"
Requires-Dist: httpcore (==1.0.5) ; python_version >= "3.10" and python_version < "3.13"
Requires-Dist: httptools (==0.6.1) ; python_version >= "3.10" and python_version < "3.13"
Requires-Dist: httpx (==0.27.0) ; python_version >= "3.10" and python_version < "3.13"
Requires-Dist: huggingface-hub (==0.23.0) ; python_version >= "3.10" and python_version < "3.13"
Requires-Dist: humancursor (==1.1.5) ; python_version >= "3.10" and python_version < "3.13"
Requires-Dist: idna (==3.7) ; python_version >= "3.10" and python_version < "3.13"
Requires-Dist: importlib-metadata (==7.1.0) ; python_version >= "3.10" and python_version < "3.13"
Requires-Dist: iniconfig (==2.0.0) ; python_version >= "3.10" and python_version < "3.13"
Requires-Dist: jinja2 (==3.1.4) ; python_version >= "3.10" and python_version < "3.13"
Requires-Dist: jwcrypto (==1.5.6) ; python_version >= "3.10" and python_version < "3.13"
Requires-Dist: litellm (==1.37.16) ; python_version >= "3.10" and python_version < "3.13"
Requires-Dist: lxml (==5.2.2) ; python_version >= "3.10" and python_version < "3.13"
Requires-Dist: markdown-it-py (==3.0.0) ; python_version >= "3.10" and python_version < "3.13"
Requires-Dist: markupsafe (==2.1.5) ; python_version >= "3.10" and python_version < "3.13"
Requires-Dist: mdurl (==0.1.2) ; python_version >= "3.10" and python_version < "3.13"
Requires-Dist: mouseinfo (==0.1.3) ; python_version >= "3.10" and python_version < "3.13"
Requires-Dist: multidict (==6.0.5) ; python_version >= "3.10" and python_version < "3.13"
Requires-Dist: numpy (==1.26.4) ; python_version >= "3.10" and python_version < "3.13"
Requires-Dist: openai (==1.30.1) ; python_version >= "3.10" and python_version < "3.13"
Requires-Dist: opencv-python (==4.9.0.80) ; python_version >= "3.10" and python_version < "3.13"
Requires-Dist: outcome (==1.3.0.post0) ; python_version >= "3.10" and python_version < "3.13"
Requires-Dist: packaging (==24.0) ; python_version >= "3.10" and python_version < "3.13"
Requires-Dist: parameterized (==0.9.0) ; python_version >= "3.10" and python_version < "3.13"
Requires-Dist: parse (==1.20.1) ; python_version >= "3.10" and python_version < "3.13"
Requires-Dist: parse-type (==0.6.2) ; python_version >= "3.10" and python_version < "3.13"
Requires-Dist: pdbp (==1.5.0) ; python_version >= "3.10" and python_version < "3.13"
Requires-Dist: pillow (==10.3.0) ; python_version >= "3.10" and python_version < "3.13"
Requires-Dist: pip (==24.0) ; python_version >= "3.10" and python_version < "3.13"
Requires-Dist: platformdirs (==4.2.2) ; python_version >= "3.10" and python_version < "3.13"
Requires-Dist: pluggy (==1.5.0) ; python_version >= "3.10" and python_version < "3.13"
Requires-Dist: py (==1.11.0) ; python_version >= "3.10" and python_version < "3.13"
Requires-Dist: pyautogen[lmm,redis] (==0.2.27) ; python_version >= "3.10" and python_version < "3.13"
Requires-Dist: pyautogui (==0.9.54) ; python_version >= "3.10" and python_version < "3.13"
Requires-Dist: pycparser (==2.22) ; python_version >= "3.10" and python_version < "3.13" and (os_name == "nt" or platform_python_implementation != "PyPy") and (implementation_name != "pypy" or platform_python_implementation != "PyPy")
Requires-Dist: pydantic (==2.7.1) ; python_version >= "3.10" and python_version < "3.13"
Requires-Dist: pydantic-core (==2.18.2) ; python_version >= "3.10" and python_version < "3.13"
Requires-Dist: pygetwindow (==0.0.9) ; python_version >= "3.10" and python_version < "3.13"
Requires-Dist: pygments (==2.18.0) ; python_version >= "3.10" and python_version < "3.13"
Requires-Dist: pymsgbox (==1.0.9) ; python_version >= "3.10" and python_version < "3.13"
Requires-Dist: pynose (==1.5.1) ; python_version >= "3.10" and python_version < "3.13"
Requires-Dist: pyobjc-core (==10.2) ; python_version >= "3.10" and python_version < "3.13" and platform_system == "Darwin"
Requires-Dist: pyobjc-framework-cocoa (==10.2) ; python_version >= "3.10" and python_version < "3.13" and platform_system == "Darwin"
Requires-Dist: pyobjc-framework-quartz (==10.2) ; python_version >= "3.10" and python_version < "3.13" and platform_system == "Darwin"
Requires-Dist: pyotp (==2.9.0) ; python_version >= "3.10" and python_version < "3.13"
Requires-Dist: pyperclip (==1.8.2) ; python_version >= "3.10" and python_version < "3.13"
Requires-Dist: pyreadline3 (==3.4.1) ; python_version >= "3.10" and python_version < "3.13" and platform_system == "Windows"
Requires-Dist: pyrect (==0.2.0) ; python_version >= "3.10" and python_version < "3.13"
Requires-Dist: pyscreeze (==0.1.30) ; python_version >= "3.10" and python_version < "3.13"
Requires-Dist: pysocks (==1.7.1) ; python_version >= "3.10" and python_version < "3.13"
Requires-Dist: pytest (==8.2.0) ; python_version >= "3.10" and python_version < "3.13"
Requires-Dist: pytest-html (==2.0.1) ; python_version >= "3.10" and python_version < "3.13"
Requires-Dist: pytest-metadata (==3.1.1) ; python_version >= "3.10" and python_version < "3.13"
Requires-Dist: pytest-ordering (==0.6) ; python_version >= "3.10" and python_version < "3.13"
Requires-Dist: pytest-rerunfailures (==14.0) ; python_version >= "3.10" and python_version < "3.13"
Requires-Dist: pytest-xdist (==3.6.1) ; python_version >= "3.10" and python_version < "3.13"
Requires-Dist: python-dotenv (==1.0.1) ; python_version >= "3.10" and python_version < "3.13"
Requires-Dist: python3-xlib (==0.15) ; platform_system == "Linux" and python_version >= "3.10" and python_version < "3.13"
Requires-Dist: pytweening (==1.2.0) ; python_version >= "3.10" and python_version < "3.13"
Requires-Dist: pywin32 (==306) ; python_version >= "3.10" and python_version < "3.13" and sys_platform == "win32"
Requires-Dist: pyyaml (==6.0.1) ; python_version >= "3.10" and python_version < "3.13"
Requires-Dist: redis (==5.0.4) ; python_version >= "3.10" and python_version < "3.13"
Requires-Dist: regex (==2024.5.15) ; python_version >= "3.10" and python_version < "3.13"
Requires-Dist: replicate (==0.26.0) ; python_version >= "3.10" and python_version < "3.13"
Requires-Dist: requests (==2.31.0) ; python_version >= "3.10" and python_version < "3.13"
Requires-Dist: rich (==13.7.1) ; python_version >= "3.10" and python_version < "3.13"
Requires-Dist: rubicon-objc (==0.4.9) ; python_version >= "3.10" and python_version < "3.13" and platform_system == "Darwin"
Requires-Dist: sbvirtualdisplay (==1.3.0) ; python_version >= "3.10" and python_version < "3.13"
Requires-Dist: selenium (==4.21.0) ; python_version >= "3.10" and python_version < "3.13"
Requires-Dist: seleniumbase (==4.27.0) ; python_version >= "3.10" and python_version < "3.13"
Requires-Dist: setuptools (==69.5.1) ; python_version >= "3.10" and python_version < "3.13"
Requires-Dist: simplejson (==3.19.2) ; python_version >= "3.10" and python_version < "3.13"
Requires-Dist: six (==1.16.0) ; python_version >= "3.10" and python_version < "3.13"
Requires-Dist: sniffio (==1.3.1) ; python_version >= "3.10" and python_version < "3.13"
Requires-Dist: sortedcontainers (==2.4.0) ; python_version >= "3.10" and python_version < "3.13"
Requires-Dist: soupsieve (==2.5) ; python_version >= "3.10" and python_version < "3.13"
Requires-Dist: starlette (==0.37.2) ; python_version >= "3.10" and python_version < "3.13"
Requires-Dist: tabcompleter (==1.3.0) ; python_version >= "3.10" and python_version < "3.13"
Requires-Dist: termcolor (==2.4.0) ; python_version >= "3.10" and python_version < "3.13"
Requires-Dist: tiktoken (==0.7.0) ; python_version >= "3.10" and python_version < "3.13"
Requires-Dist: tokenizers (==0.19.1) ; python_version >= "3.10" and python_version < "3.13"
Requires-Dist: tomli (==2.0.1) ; python_version >= "3.10" and python_version < "3.11"
Requires-Dist: tqdm (==4.66.4) ; python_version >= "3.10" and python_version < "3.13"
Requires-Dist: trio (==0.25.1) ; python_version >= "3.10" and python_version < "3.13"
Requires-Dist: trio-websocket (==0.11.1) ; python_version >= "3.10" and python_version < "3.13"
Requires-Dist: typing-extensions (==4.11.0) ; python_version >= "3.10" and python_version < "3.13"
Requires-Dist: urllib3[socks] (==2.2.1) ; python_version >= "3.10" and python_version < "3.13"
Requires-Dist: uvicorn[standard] (==0.29.0) ; python_version >= "3.10" and python_version < "3.13"
Requires-Dist: uvloop (==0.19.0) ; (sys_platform != "win32" and sys_platform != "cygwin") and platform_python_implementation != "PyPy" and python_version >= "3.10" and python_version < "3.13"
Requires-Dist: watchfiles (==0.21.0) ; python_version >= "3.10" and python_version < "3.13"
Requires-Dist: websockets (==12.0) ; python_version >= "3.10" and python_version < "3.13"
Requires-Dist: websockify (==0.11.0) ; python_version >= "3.10" and python_version < "3.13"
Requires-Dist: wheel (==0.43.0) ; python_version >= "3.10" and python_version < "3.13"
Requires-Dist: wsproto (==1.2.0) ; python_version >= "3.10" and python_version < "3.13"
Requires-Dist: yarl (==1.9.4) ; python_version >= "3.10" and python_version < "3.13"
Requires-Dist: zipp (==3.18.2) ; python_version >= "3.10" and python_version < "3.13"
